README
setup.py
bambu_buffer/__init__.py
bambu_buffer/apps.py
bambu_buffer/exceptions.py
bambu_buffer/log.py
bambu_buffer/models.py
bambu_buffer/receivers.py
bambu_buffer/settings.py
bambu_buffer/tests.py
bambu_buffer/urls.py
bambu_buffer/views.py
bambu_buffer.egg-info/PKG-INFO
bambu_buffer.egg-info/SOURCES.txt
bambu_buffer.egg-info/dependency_links.txt
bambu_buffer.egg-info/requires.txt
bambu_buffer.egg-info/top_level.txt
bambu_buffer/migrations/0001_initial.py
bambu_buffer/migrations/__init__.py
bambu_buffer/templates/buffer/base.html
bambu_buffer/templates/buffer/profiles.html