Metadata-Version: 1.1
Name: bambu-buffer
Version: 3.3.2
Summary: Post to Buffer and manage profile settings through a Django-powered site
Home-page: https://github.com/iamsteadman/bambu-buffer
Author: Steadman
Author-email: mark@steadman.io
License: UNKNOWN
Platform: UNKNOWN
Classifier: Development Status :: 4 - Beta
Classifier: Environment :: Web Environment
Classifier: Framework :: Django
